[
    {
        "id": 1,
        "title": "Front-End Developer",
        "company": "CodeCo",
        "icon": "fab fa-react",
        "iconBg": "bg-blue-600 text-white",
        "postedDate": "2026-02-10",
        "salary": "$80k - $120k/year",
        "description": "We are looking for an experienced Front-End Developer to join our team and build responsive user interfaces.",
        "type": "Technology",
        "location": "On Site",
        "category": "full-time",
        "status": "active",
        "expiredDate": "2026-03-30"
    },
    {
        "id": 2,
        "title": "UX/UI Designer",
        "company": "EcoWorks",
        "icon": "fab fa-figma",
        "iconBg": "bg-green-500 text-white",
        "postedDate": "2026-02-11",
        "salary": "$75k - $110k/year",
        "description": "Design user-centric experiences for sustainable products.",
        "type": "Technology",
        "location": "Hybrid",
        "category": "full-time",
        "status": "active",
        "expiredDate": "2026-03-30"
    },
    {
        "id": 3,
        "title": "Back-End Engineer",
        "company": "TechFlow",
        "icon": "fas fa-server",
        "iconBg": "bg-yellow-500 text-white",
        "postedDate": "2026-02-09",
        "salary": "$90k - $130k/year",
        "description": "Build scalable APIs and microservices for our growing platform.",
        "type": "Technology",
        "location": "Remote",
        "category": "full-time",
        "status": "active",
        "expiredDate": "2026-03-30"
    },
    {
        "id": 4,
        "title": "Product Manager",
        "company": "InnoSoft",
        "icon": "fas fa-rocket",
        "iconBg": "bg-purple-500 text-white",
        "postedDate": "2026-02-07",
        "salary": "$100k - $150k/year",
        "description": "Lead the product vision and strategy for our core products.",
        "type": "Management",
        "location": "On Site",
        "category": "full-time",
        "status": "active",
        "expiredDate": "2026-03-30"
    }
]